s3_file_downloader/__init__.py
s3_file_downloader/downloader.py
s3_file_downloader/session.py
s3_file_downloader/utils.py
s3_file_downloader-0.1.0.dist-info/METADATA
s3_file_downloader-0.1.0.dist-info/WHEEL
s3_file_downloader-0.1.0.dist-info/top_level.txt
s3_file_downloader-0.1.0.dist-info/RECORD
