Metadata-Version: 2.4
Name: s3-file-downloader
Version: 0.1.0
Summary: Simple library to list and download files from Amazon S3.
Author-email: Divya Idupulapati <idupulapatidivya@gmail.com>, Pavan Sairam Marella <pavanmarella72@gmail.com>
License: MIT
Keywords: aws,s3,downloader
Requires-Python: >=3.8
Requires-Dist: boto3
